[
  {
    "Name": "Aatrox",
    "Class": "Fighter",
    "Role": "TOP",
    "Tier": "God",
    "Score": 77.17,
    "Trend": -5.29,
    "Win %": "49.54%",
    "Role %": "92.59%",
    "Pick %": "7.61%",
    "Ban %": "6.47%",
    "KDA": 1.84
  },
  {
    "Name": "Ahri",
    "Class": "Mage",
    "Role": "MID",
    "Tier": "God",
    "Score": 80.34,
    "Trend": -7.49,
    "Win %": "50.38%",
    "Role %": "94.77%",
    "Pick %": "10.83%",
    "Ban %": "13.10%",
    "KDA": 2.41
  },
  {
    "Name": "Akali",
    "Class": "Assassin",
    "Role": "MID",
    "Tier": "S",
    "Score": 62.64,
    "Trend": -0.47,
    "Win %": "49.61%",
    "Role %": "64.32%",
    "Pick %": "6.53%",
    "Ban %": "15.19%",
    "KDA": 2.26
  },
  {
    "Name": "Akali",
    "Class": "Assassin",
    "Role": "TOP",
    "Tier": "A",
    "Score": 49.62,
    "Trend": -1.6,
    "Win %": "48.14%",
    "Role %": "34.81%",
    "Pick %": "3.32%",
    "Ban %": "15.19%",
    "KDA": 1.98
  },
  {
    "Name": "Akshan",
    "Class": "Marksman",
    "Role": "MID",
    "Tier": "A",
    "Score": 52.54,
    "Trend": 1.41,
    "Win %": "50.97%",
    "Role %": "61.05%",
    "Pick %": "3.64%",
    "Ban %": "10.18%",
    "KDA": 2.13
  },
  {
    "Name": "Akshan",
    "Class": "Marksman",
    "Role": "TOP",
    "Tier": "B",
    "Score": 44.81,
    "Trend": 4.4,
    "Win %": "51.57%",
    "Role %": "29.06%",
    "Pick %": "1.66%",
    "Ban %": "10.18%",
    "KDA": 1.88
  },
  {
    "Name": "Alistar",
    "Class": "Tank",
    "Role": "SUPPORT",
    "Tier": "A",
    "Score": 47.79,
    "Trend": 0.68,
    "Win %": "50.26%",
    "Role %": "96.87%",
    "Pick %": "3.49%",
    "Ban %": "0.85%",
    "KDA": 2.47
  },
  {
    "Name": "Amumu",
    "Class": "Tank",
    "Role": "JUNGLE",
    "Tier": "C",
    "Score": 38.79,
    "Trend": 2.96,
    "Win %": "49.97%",
    "Role %": "83.60%",
    "Pick %": "2.28%",
    "Ban %": "0.94%",
    "KDA": 2.47
  },
  {
    "Name": "Amumu",
    "Class": "Tank",
    "Role": "SUPPORT",
    "Tier": "D",
    "Score": 33.07,
    "Trend": 1.53,
    "Win %": "48.81%",
    "Role %": "13.65%",
    "Pick %": "0.34%",
    "Ban %": "1.01%",
    "KDA": 1.95
  },
  {
    "Name": "Anivia",
    "Class": "Mage",
    "Role": "MID",
    "Tier": "A",
    "Score": 50.53,
    "Trend": -2.84,
    "Win %": "51.06%",
    "Role %": "78.88%",
    "Pick %": "2.71%",
    "Ban %": "2.81%",
    "KDA": 2.5
  },
  {
    "Name": "Anivia",
    "Class": "Mage",
    "Role": "SUPPORT",
    "Tier": "D",
    "Score": 31.88,
    "Trend": 5.81,
    "Win %": "47.75%",
    "Role %": "13.87%",
    "Pick %": "0.42%",
    "Ban %": "2.81%",
    "KDA": 2.08
  },
  {
    "Name": "Annie",
    "Class": "Mage",
    "Role": "MID",
    "Tier": "B",
    "Score": 43.52,
    "Trend": -2.55,
    "Win %": "49.86%",
    "Role %": "82.56%",
    "Pick %": "1.74%",
    "Ban %": "0.69%",
    "KDA": 2.23
  },
  {
    "Name": "Annie",
    "Class": "Mage",
    "Role": "SUPPORT",
    "Tier": "D",
    "Score": 26.92,
    "Trend": -7.49,
    "Win %": "45.75%",
    "Role %": "11.76%",
    "Pick %": "0.25%",
    "Ban %": "0.74%",
    "KDA": 1.94
  },
  {
    "Name": "Aphelios",
    "Class": "Marksman",
    "Role": "ADC",
    "Tier": "C",
    "Score": 35.84,
    "Trend": 3.19,
    "Win %": "45.38%",
    "Role %": "96.78%",
    "Pick %": "7.30%",
    "Ban %": "1.26%",
    "KDA": 1.86
  },
  {
    "Name": "Ashe",
    "Class": "Marksman",
    "Role": "ADC",
    "Tier": "B",
    "Score": 46.51,
    "Trend": -2.5,
    "Win %": "50.05%",
    "Role %": "78.58%",
    "Pick %": "6.67%",
    "Ban %": "1.08%",
    "KDA": 2.3
  },
  {
    "Name": "Ashe",
    "Class": "Marksman",
    "Role": "SUPPORT",
    "Tier": "C",
    "Score": 39.18,
    "Trend": 0.98,
    "Win %": "49.51%",
    "Role %": "17.14%",
    "Pick %": "1.44%",
    "Ban %": "1.16%",
    "KDA": 2.27
  },
  {
    "Name": "Aurelion Sol",
    "Class": "Mage",
    "Role": "MID",
    "Tier": "C",
    "Score": 39.53,
    "Trend": -3.42,
    "Win %": "49.37%",
    "Role %": "85.90%",
    "Pick %": "0.76%",
    "Ban %": "0.34%",
    "KDA": 2.25
  },
  {
    "Name": "Azir",
    "Class": "Mage",
    "Role": "MID",
    "Tier": "C",
    "Score": 37.67,
    "Trend": -4.52,
    "Win %": "47.20%",
    "Role %": "81.99%",
    "Pick %": "1.75%",
    "Ban %": "0.38%",
    "KDA": 2.03
  },
  {
    "Name": "Azir",
    "Class": "Mage",
    "Role": "TOP",
    "Tier": "D",
    "Score": 22.29,
    "Trend": 0,
    "Win %": "46.63%",
    "Role %": "12.99%",
    "Pick %": "0.26%",
    "Ban %": "0.36%",
    "KDA": 1.74
  },
  {
    "Name": "Bard",
    "Class": "Support",
    "Role": "SUPPORT",
    "Tier": "A",
    "Score": 48.82,
    "Trend": -2.21,
    "Win %": "50.31%",
    "Role %": "97.06%",
    "Pick %": "3.25%",
    "Ban %": "0.57%",
    "KDA": 2.87
  },
  {
    "Name": "Blitzcrank",
    "Class": "Tank",
    "Role": "SUPPORT",
    "Tier": "S",
    "Score": 63.13,
    "Trend": -0.45,
    "Win %": "50.50%",
    "Role %": "98.21%",
    "Pick %": "7.01%",
    "Ban %": "16.84%",
    "KDA": 2.41
  },
  {
    "Name": "Brand",
    "Class": "Mage",
    "Role": "SUPPORT",
    "Tier": "B",
    "Score": 44.29,
    "Trend": 1.33,
    "Win %": "49.97%",
    "Role %": "68.46%",
    "Pick %": "3.32%",
    "Ban %": "4.88%",
    "KDA": 1.77
  },
  {
    "Name": "Brand",
    "Class": "Mage",
    "Role": "MID",
    "Tier": "B",
    "Score": 40.49,
    "Trend": 2.19,
    "Win %": "50.36%",
    "Role %": "17.50%",
    "Pick %": "0.83%",
    "Ban %": "5.34%",
    "KDA": 2.01
  },
  {
    "Name": "Braum",
    "Class": "Support",
    "Role": "SUPPORT",
    "Tier": "B",
    "Score": 43.77,
    "Trend": 4.16,
    "Win %": "48.63%",
    "Role %": "98.06%",
    "Pick %": "2.70%",
    "Ban %": "0.40%",
    "KDA": 2.84
  },
  {
    "Name": "Caitlyn",
    "Class": "Marksman",
    "Role": "ADC",
    "Tier": "A",
    "Score": 48.84,
    "Trend": -6.38,
    "Win %": "47.90%",
    "Role %": "96.58%",
    "Pick %": "9.21%",
    "Ban %": "6.68%",
    "KDA": 2.12
  },
  {
    "Name": "Camille",
    "Class": "Fighter",
    "Role": "TOP",
    "Tier": "S",
    "Score": 60.38,
    "Trend": -3.25,
    "Win %": "49.70%",
    "Role %": "94.75%",
    "Pick %": "5.07%",
    "Ban %": "3.44%",
    "KDA": 1.84
  },
  {
    "Name": "Cassiopeia",
    "Class": "Mage",
    "Role": "MID",
    "Tier": "B",
    "Score": 44.23,
    "Trend": 0.35,
    "Win %": "50.33%",
    "Role %": "73.14%",
    "Pick %": "2.06%",
    "Ban %": "1.68%",
    "KDA": 1.99
  },
  {
    "Name": "Cassiopeia",
    "Class": "Mage",
    "Role": "TOP",
    "Tier": "D",
    "Score": 28.08,
    "Trend": -7.39,
    "Win %": "48.43%",
    "Role %": "15.53%",
    "Pick %": "0.47%",
    "Ban %": "1.70%",
    "KDA": 1.76
  },
  {
    "Name": "Cho'Gath",
    "Class": "Tank",
    "Role": "TOP",
    "Tier": "A",
    "Score": 52,
    "Trend": 9.25,
    "Win %": "52.63%",
    "Role %": "66.06%",
    "Pick %": "2.42%",
    "Ban %": "0.93%",
    "KDA": 2.03
  },
  {
    "Name": "Cho'Gath",
    "Class": "Tank",
    "Role": "MID",
    "Tier": "B",
    "Score": 45.53,
    "Trend": 4.64,
    "Win %": "52.89%",
    "Role %": "19.87%",
    "Pick %": "0.59%",
    "Ban %": "0.93%",
    "KDA": 2.27
  },
  {
    "Name": "Corki",
    "Class": "Marksman",
    "Role": "MID",
    "Tier": "C",
    "Score": 36.72,
    "Trend": -2.28,
    "Win %": "47.16%",
    "Role %": "89.96%",
    "Pick %": "1.45%",
    "Ban %": "0.36%",
    "KDA": 2.05
  },
  {
    "Name": "Darius",
    "Class": "Fighter",
    "Role": "TOP",
    "Tier": "God",
    "Score": 85.61,
    "Trend": -5.85,
    "Win %": "49.82%",
    "Role %": "93.23%",
    "Pick %": "7.79%",
    "Ban %": "18.09%",
    "KDA": 1.75
  },
  {
    "Name": "Diana",
    "Class": "Fighter",
    "Role": "JUNGLE",
    "Tier": "God",
    "Score": 75,
    "Trend": -11.75,
    "Win %": "51.74%",
    "Role %": "82.65%",
    "Pick %": "8.65%",
    "Ban %": "10.88%",
    "KDA": 2.46
  },
  {
    "Name": "Diana",
    "Class": "Fighter",
    "Role": "MID",
    "Tier": "B",
    "Score": 44.98,
    "Trend": -1.05,
    "Win %": "50.71%",
    "Role %": "15.83%",
    "Pick %": "1.72%",
    "Ban %": "10.88%",
    "KDA": 2.1
  },
  {
    "Name": "Dr. Mundo",
    "Class": "Marksman",
    "Role": "TOP",
    "Tier": "B",
    "Score": 46.54,
    "Trend": -1.14,
    "Win %": "50.99%",
    "Role %": "85.17%",
    "Pick %": "2.13%",
    "Ban %": "1.31%",
    "KDA": 2.05
  },
  {
    "Name": "Draven",
    "Class": "Fighter",
    "Role": "ADC",
    "Tier": "B",
    "Score": 41.87,
    "Trend": -1.32,
    "Win %": "48.92%",
    "Role %": "94.24%",
    "Pick %": "5.83%",
    "Ban %": "11.25%",
    "KDA": 2
  },
  {
    "Name": "Ekko",
    "Class": "Assassin",
    "Role": "JUNGLE",
    "Tier": "A",
    "Score": 54.65,
    "Trend": -3.32,
    "Win %": "50.82%",
    "Role %": "63.48%",
    "Pick %": "4.98%",
    "Ban %": "3.79%",
    "KDA": 2.7
  },
  {
    "Name": "Ekko",
    "Class": "Assassin",
    "Role": "MID",
    "Tier": "B",
    "Score": 46.01,
    "Trend": 1.2,
    "Win %": "49.87%",
    "Role %": "34.02%",
    "Pick %": "2.52%",
    "Ban %": "3.79%",
    "KDA": 2.16
  },
  {
    "Name": "Elise",
    "Class": "Mage",
    "Role": "JUNGLE",
    "Tier": "C",
    "Score": 33.9,
    "Trend": 1.96,
    "Win %": "49.11%",
    "Role %": "92.08%",
    "Pick %": "1.57%",
    "Ban %": "0.86%",
    "KDA": 2.51
  },
  {
    "Name": "Evelynn",
    "Class": "Assassin",
    "Role": "JUNGLE",
    "Tier": "B",
    "Score": 40.83,
    "Trend": -0.32,
    "Win %": "48.26%",
    "Role %": "98.47%",
    "Pick %": "3.16%",
    "Ban %": "5.63%",
    "KDA": 2.73
  },
  {
    "Name": "Ezreal",
    "Class": "Marksman",
    "Role": "ADC",
    "Tier": "God",
    "Score": 89.22,
    "Trend": 1.78,
    "Win %": "50.16%",
    "Role %": "96.07%",
    "Pick %": "22.55%",
    "Ban %": "5.82%",
    "KDA": 2.37
  },
  {
    "Name": "Fiddlesticks",
    "Class": "Mage",
    "Role": "JUNGLE",
    "Tier": "A",
    "Score": 47.9,
    "Trend": -0.04,
    "Win %": "51.65%",
    "Role %": "89.05%",
    "Pick %": "3.15%",
    "Ban %": "2.46%",
    "KDA": 2.64
  },
  {
    "Name": "Fiora",
    "Class": "Fighter",
    "Role": "TOP",
    "Tier": "God",
    "Score": 74.85,
    "Trend": -2.69,
    "Win %": "51.10%",
    "Role %": "97.41%",
    "Pick %": "6.14%",
    "Ban %": "14.82%",
    "KDA": 1.7
  },
  {
    "Name": "Fizz",
    "Class": "Assassin",
    "Role": "MID",
    "Tier": "A",
    "Score": 54.63,
    "Trend": 0.01,
    "Win %": "51.39%",
    "Role %": "95.18%",
    "Pick %": "3.74%",
    "Ban %": "5.44%",
    "KDA": 2.44
  },
  {
    "Name": "Galio",
    "Class": "Tank",
    "Role": "MID",
    "Tier": "B",
    "Score": 47.11,
    "Trend": -1.94,
    "Win %": "50.34%",
    "Role %": "73.80%",
    "Pick %": "2.05%",
    "Ban %": "0.40%",
    "KDA": 2.55
  },
  {
    "Name": "Galio",
    "Class": "Tank",
    "Role": "SUPPORT",
    "Tier": "C",
    "Score": 34.05,
    "Trend": -1.87,
    "Win %": "48.32%",
    "Role %": "23.91%",
    "Pick %": "0.63%",
    "Ban %": "0.41%",
    "KDA": 2.19
  },
  {
    "Name": "Gangplank",
    "Class": "Fighter",
    "Role": "TOP",
    "Tier": "God",
    "Score": 88.94,
    "Trend": 1.38,
    "Win %": "47.44%",
    "Role %": "85.96%",
    "Pick %": "9.16%",
    "Ban %": "15.52%",
    "KDA": 1.85
  },
  {
    "Name": "Gangplank",
    "Class": "Fighter",
    "Role": "MID",
    "Tier": "C",
    "Score": 38.56,
    "Trend": -0.62,
    "Win %": "47.55%",
    "Role %": "13.32%",
    "Pick %": "1.53%",
    "Ban %": "14.98%",
    "KDA": 2.06
  },
  {
    "Name": "Garen",
    "Class": "Fighter",
    "Role": "TOP",
    "Tier": "God",
    "Score": 73.45,
    "Trend": -2.81,
    "Win %": "51.73%",
    "Role %": "85.69%",
    "Pick %": "6.21%",
    "Ban %": "3.20%",
    "KDA": 1.99
  },
  {
    "Name": "Gnar",
    "Class": "Fighter",
    "Role": "TOP",
    "Tier": "B",
    "Score": 45.95,
    "Trend": -1.3,
    "Win %": "48.40%",
    "Role %": "96.66%",
    "Pick %": "3.38%",
    "Ban %": "0.71%",
    "KDA": 1.82
  },
  {
    "Name": "Gragas",
    "Class": "Fighter",
    "Role": "MID",
    "Tier": "C",
    "Score": 38.96,
    "Trend": -5.2,
    "Win %": "49.69%",
    "Role %": "12.52%",
    "Pick %": "0.42%",
    "Ban %": "0.28%",
    "KDA": 2.24
  },
  {
    "Name": "Gragas",
    "Class": "Fighter",
    "Role": "TOP",
    "Tier": "C",
    "Score": 36.77,
    "Trend": 2.44,
    "Win %": "48.10%",
    "Role %": "53.37%",
    "Pick %": "1.82%",
    "Ban %": "0.28%",
    "KDA": 1.95
  },
  {
    "Name": "Gragas",
    "Class": "Fighter",
    "Role": "SUPPORT",
    "Tier": "D",
    "Score": 29.64,
    "Trend": -3.64,
    "Win %": "46.25%",
    "Role %": "15.79%",
    "Pick %": "0.49%",
    "Ban %": "0.28%",
    "KDA": 2.18
  },
  {
    "Name": "Gragas",
    "Class": "Fighter",
    "Role": "JUNGLE",
    "Tier": "D",
    "Score": 28.82,
    "Trend": 7.78,
    "Win %": "48.52%",
    "Role %": "19.05%",
    "Pick %": "0.57%",
    "Ban %": "0.28%",
    "KDA": 2.63
  },
  {
    "Name": "Graves",
    "Class": "Marksman",
    "Role": "JUNGLE",
    "Tier": "God",
    "Score": 90.33,
    "Trend": 5.16,
    "Win %": "50.20%",
    "Role %": "77.10%",
    "Pick %": "11.88%",
    "Ban %": "13.65%",
    "KDA": 2.52
  },
  {
    "Name": "Graves",
    "Class": "Marksman",
    "Role": "TOP",
    "Tier": "A",
    "Score": 47.95,
    "Trend": 3.06,
    "Win %": "50.40%",
    "Role %": "17.16%",
    "Pick %": "2.65%",
    "Ban %": "13.65%",
    "KDA": 1.67
  },
  {
    "Name": "Gwen",
    "Class": "Fighter",
    "Role": "TOP",
    "Tier": "A",
    "Score": 52.5,
    "Trend": 9.79,
    "Win %": "48.53%",
    "Role %": "82.72%",
    "Pick %": "4.56%",
    "Ban %": "2.01%",
    "KDA": 1.65
  },
  {
    "Name": "Gwen",
    "Class": "Fighter",
    "Role": "JUNGLE",
    "Tier": "D",
    "Score": 33.81,
    "Trend": 5.62,
    "Win %": "51.01%",
    "Role %": "13.30%",
    "Pick %": "0.72%",
    "Ban %": "2.01%",
    "KDA": 2.36
  },
  {
    "Name": "Hecarim",
    "Class": "Fighter",
    "Role": "JUNGLE",
    "Tier": "A",
    "Score": 48.1,
    "Trend": 14.03,
    "Win %": "49.03%",
    "Role %": "97.76%",
    "Pick %": "4.37%",
    "Ban %": "3.46%",
    "KDA": 2.79
  },
  {
    "Name": "Heimerdinger",
    "Class": "Mage",
    "Role": "MID",
    "Tier": "B",
    "Score": 42.02,
    "Trend": 2.97,
    "Win %": "51.69%",
    "Role %": "39.55%",
    "Pick %": "0.89%",
    "Ban %": "1.33%",
    "KDA": 1.83
  },
  {
    "Name": "Heimerdinger",
    "Class": "Mage",
    "Role": "ADC",
    "Tier": "D",
    "Score": 32.88,
    "Trend": 5.05,
    "Win %": "52.11%",
    "Role %": "14.34%",
    "Pick %": "0.28%",
    "Ban %": "1.33%",
    "KDA": 2.01
  },
  {
    "Name": "Heimerdinger",
    "Class": "Mage",
    "Role": "SUPPORT",
    "Tier": "D",
    "Score": 30.41,
    "Trend": -1.05,
    "Win %": "48.02%",
    "Role %": "11.22%",
    "Pick %": "0.24%",
    "Ban %": "1.46%",
    "KDA": 1.75
  },
  {
    "Name": "Heimerdinger",
    "Class": "Mage",
    "Role": "TOP",
    "Tier": "D",
    "Score": 30.14,
    "Trend": -1.67,
    "Win %": "49.27%",
    "Role %": "33.68%",
    "Pick %": "0.70%",
    "Ban %": "1.33%",
    "KDA": 1.58
  },
  {
    "Name": "Illaoi",
    "Class": "Fighter",
    "Role": "TOP",
    "Tier": "B",
    "Score": 43.84,
    "Trend": -1.73,
    "Win %": "49.98%",
    "Role %": "92.53%",
    "Pick %": "2.83%",
    "Ban %": "4.47%",
    "KDA": 1.36
  },
  {
    "Name": "Irelia",
    "Class": "Fighter",
    "Role": "TOP",
    "Tier": "S",
    "Score": 70.4,
    "Trend": -10.21,
    "Win %": "49.06%",
    "Role %": "56.14%",
    "Pick %": "5.94%",
    "Ban %": "21.49%",
    "KDA": 1.55
  },
  {
    "Name": "Irelia",
    "Class": "Fighter",
    "Role": "MID",
    "Tier": "A",
    "Score": 52.92,
    "Trend": -2.9,
    "Win %": "49.07%",
    "Role %": "42.09%",
    "Pick %": "4.61%",
    "Ban %": "21.49%",
    "KDA": 1.74
  },
  {
    "Name": "Ivern",
    "Class": "Support",
    "Role": "JUNGLE",
    "Tier": "D",
    "Score": 32.53,
    "Trend": -0.84,
    "Win %": "47.66%",
    "Role %": "78.15%",
    "Pick %": "1.21%",
    "Ban %": "0.44%",
    "KDA": 3.1
  },
  {
    "Name": "Ivern",
    "Class": "Support",
    "Role": "SUPPORT",
    "Tier": "D",
    "Score": 22.55,
    "Trend": -7.72,
    "Win %": "42.25%",
    "Role %": "11.22%",
    "Pick %": "0.17%",
    "Ban %": "0.41%",
    "KDA": 2.54
  },
  {
    "Name": "Janna",
    "Class": "Support",
    "Role": "SUPPORT",
    "Tier": "S",
    "Score": 58.37,
    "Trend": 0.3,
    "Win %": "52.99%",
    "Role %": "97.02%",
    "Pick %": "4.33%",
    "Ban %": "0.97%",
    "KDA": 3.12
  },
  {
    "Name": "Jarvan IV",
    "Class": "Tank",
    "Role": "JUNGLE",
    "Tier": "B",
    "Score": 42.78,
    "Trend": -8.09,
    "Win %": "48.89%",
    "Role %": "88.90%",
    "Pick %": "2.87%",
    "Ban %": "0.44%",
    "KDA": 3.12
  },
  {
    "Name": "Jax",
    "Class": "Fighter",
    "Role": "TOP",
    "Tier": "God",
    "Score": 72.03,
    "Trend": -6.25,
    "Win %": "50.89%",
    "Role %": "84.23%",
    "Pick %": "6.26%",
    "Ban %": "10.29%",
    "KDA": 1.62
  },
  {
    "Name": "Jax",
    "Class": "Fighter",
    "Role": "JUNGLE",
    "Tier": "C",
    "Score": 35.95,
    "Trend": 4.16,
    "Win %": "51.89%",
    "Role %": "13.66%",
    "Pick %": "1.01%",
    "Ban %": "9.86%",
    "KDA": 2.11
  },
  {
    "Name": "Jayce",
    "Class": "Fighter",
    "Role": "TOP",
    "Tier": "B",
    "Score": 43.44,
    "Trend": 3.65,
    "Win %": "47.76%",
    "Role %": "82.08%",
    "Pick %": "3.42%",
    "Ban %": "0.76%",
    "KDA": 1.66
  },
  {
    "Name": "Jayce",
    "Class": "Fighter",
    "Role": "MID",
    "Tier": "C",
    "Score": 36.24,
    "Trend": -1.49,
    "Win %": "48.62%",
    "Role %": "15.68%",
    "Pick %": "0.61%",
    "Ban %": "0.74%",
    "KDA": 1.98
  },
  {
    "Name": "Jhin",
    "Class": "Marksman",
    "Role": "ADC",
    "Tier": "God",
    "Score": 83.9,
    "Trend": -4.79,
    "Win %": "51.35%",
    "Role %": "97.27%",
    "Pick %": "18.69%",
    "Ban %": "4.49%",
    "KDA": 2.83
  },
  {
    "Name": "Jinx",
    "Class": "Marksman",
    "Role": "ADC",
    "Tier": "A",
    "Score": 51.92,
    "Trend": -12.1,
    "Win %": "49.39%",
    "Role %": "98.56%",
    "Pick %": "9.68%",
    "Ban %": "2.60%",
    "KDA": 2.14
  },
  {
    "Name": "Kai'Sa",
    "Class": "Marksman",
    "Role": "ADC",
    "Tier": "S",
    "Score": 70.6,
    "Trend": 1.79,
    "Win %": "50.47%",
    "Role %": "93.99%",
    "Pick %": "15.60%",
    "Ban %": "2.82%",
    "KDA": 2.38
  },
  {
    "Name": "Kalista",
    "Class": "Marksman",
    "Role": "ADC",
    "Tier": "C",
    "Score": 38.32,
    "Trend": 2.55,
    "Win %": "50.07%",
    "Role %": "90.82%",
    "Pick %": "3.37%",
    "Ban %": "1.12%",
    "KDA": 2.29
  },
  {
    "Name": "Karma",
    "Class": "Mage",
    "Role": "SUPPORT",
    "Tier": "S",
    "Score": 64.62,
    "Trend": -0.09,
    "Win %": "49.22%",
    "Role %": "81.55%",
    "Pick %": "8.87%",
    "Ban %": "4.71%",
    "KDA": 2.67
  },
  {
    "Name": "Karma",
    "Class": "Mage",
    "Role": "MID",
    "Tier": "B",
    "Score": 45.59,
    "Trend": 0,
    "Win %": "50.06%",
    "Role %": "10.58%",
    "Pick %": "1.24%",
    "Ban %": "4.71%",
    "KDA": 2.81
  },
  {
    "Name": "Karthus",
    "Class": "Mage",
    "Role": "JUNGLE",
    "Tier": "B",
    "Score": 45.52,
    "Trend": -3.36,
    "Win %": "49.40%",
    "Role %": "68.00%",
    "Pick %": "3.62%",
    "Ban %": "9.97%",
    "KDA": 2.48
  },
  {
    "Name": "Karthus",
    "Class": "Mage",
    "Role": "MID",
    "Tier": "B",
    "Score": 43.34,
    "Trend": 0,
    "Win %": "51.99%",
    "Role %": "10.91%",
    "Pick %": "0.54%",
    "Ban %": "9.97%",
    "KDA": 2.15
  },
  {
    "Name": "Karthus",
    "Class": "Mage",
    "Role": "ADC",
    "Tier": "C",
    "Score": 38.07,
    "Trend": -2.57,
    "Win %": "53.23%",
    "Role %": "15.68%",
    "Pick %": "0.92%",
    "Ban %": "9.97%",
    "KDA": 2.17
  },
  {
    "Name": "Kassadin",
    "Class": "Assassin",
    "Role": "MID",
    "Tier": "A",
    "Score": 53.59,
    "Trend": 0.53,
    "Win %": "51.80%",
    "Role %": "95.40%",
    "Pick %": "3.25%",
    "Ban %": "8.73%",
    "KDA": 2.33
  },
  {
    "Name": "Katarina",
    "Class": "Assassin",
    "Role": "MID",
    "Tier": "God",
    "Score": 78.43,
    "Trend": 4.98,
    "Win %": "50.46%",
    "Role %": "93.85%",
    "Pick %": "10.26%",
    "Ban %": "15.41%",
    "KDA": 2.25
  },
  {
    "Name": "Kayle",
    "Class": "Fighter",
    "Role": "TOP",
    "Tier": "S",
    "Score": 69.22,
    "Trend": 0.13,
    "Win %": "53.33%",
    "Role %": "77.44%",
    "Pick %": "5.17%",
    "Ban %": "3.03%",
    "KDA": 1.8
  },
  {
    "Name": "Kayle",
    "Class": "Fighter",
    "Role": "MID",
    "Tier": "B",
    "Score": 47.54,
    "Trend": -2.48,
    "Win %": "52.86%",
    "Role %": "19.68%",
    "Pick %": "1.29%",
    "Ban %": "3.03%",
    "KDA": 2.21
  },
  {
    "Name": "Kayn",
    "Class": "Fighter",
    "Role": "JUNGLE",
    "Tier": "God",
    "Score": 76.23,
    "Trend": -11.46,
    "Win %": "50.58%",
    "Role %": "96.03%",
    "Pick %": "9.56%",
    "Ban %": "11.92%",
    "KDA": 2.35
  },
  {
    "Name": "Kennen",
    "Class": "Mage",
    "Role": "MID",
    "Tier": "B",
    "Score": 44.02,
    "Trend": -0.85,
    "Win %": "52.09%",
    "Role %": "18.18%",
    "Pick %": "0.42%",
    "Ban %": "0.63%",
    "KDA": 2.37
  },
  {
    "Name": "Kennen",
    "Class": "Mage",
    "Role": "TOP",
    "Tier": "B",
    "Score": 40.18,
    "Trend": 1.42,
    "Win %": "49.44%",
    "Role %": "77.30%",
    "Pick %": "1.87%",
    "Ban %": "0.63%",
    "KDA": 1.93
  },
  {
    "Name": "Kha'Zix",
    "Class": "Assassin",
    "Role": "JUNGLE",
    "Tier": "S",
    "Score": 70.76,
    "Trend": -11.07,
    "Win %": "51.47%",
    "Role %": "98.41%",
    "Pick %": "8.01%",
    "Ban %": "8.49%",
    "KDA": 2.55
  },
  {
    "Name": "Kindred",
    "Class": "Marksman",
    "Role": "JUNGLE",
    "Tier": "A",
    "Score": 47.68,
    "Trend": 4.12,
    "Win %": "50.56%",
    "Role %": "93.10%",
    "Pick %": "4.18%",
    "Ban %": "3.69%",
    "KDA": 2.25
  },
  {
    "Name": "Kled",
    "Class": "Fighter",
    "Role": "MID",
    "Tier": "A",
    "Score": 52.64,
    "Trend": 0.43,
    "Win %": "56.29%",
    "Role %": "10.10%",
    "Pick %": "0.18%",
    "Ban %": "0.88%",
    "KDA": 2.7
  },
  {
    "Name": "Kled",
    "Class": "Fighter",
    "Role": "TOP",
    "Tier": "A",
    "Score": 49.41,
    "Trend": 6.2,
    "Win %": "52.39%",
    "Role %": "86.00%",
    "Pick %": "1.64%",
    "Ban %": "0.84%",
    "KDA": 2.38
  },
  {
    "Name": "Kog'Maw",
    "Class": "Marksman",
    "Role": "ADC",
    "Tier": "B",
    "Score": 41.49,
    "Trend": 0.53,
    "Win %": "53.22%",
    "Role %": "87.51%",
    "Pick %": "2.39%",
    "Ban %": "0.58%",
    "KDA": 2.19
  },
  {
    "Name": "LeBlanc",
    "Class": "Assassin",
    "Role": "MID",
    "Tier": "A",
    "Score": 49.32,
    "Trend": -0.69,
    "Win %": "46.38%",
    "Role %": "92.65%",
    "Pick %": "4.51%",
    "Ban %": "8.09%",
    "KDA": 2.56
  },
  {
    "Name": "Lee Sin",
    "Class": "Fighter",
    "Role": "JUNGLE",
    "Tier": "God",
    "Score": 72.07,
    "Trend": -15.01,
    "Win %": "46.13%",
    "Role %": "92.90%",
    "Pick %": "10.94%",
    "Ban %": "9.32%",
    "KDA": 2.54
  },
  {
    "Name": "Leona",
    "Class": "Tank",
    "Role": "SUPPORT",
    "Tier": "S",
    "Score": 60.22,
    "Trend": 1.72,
    "Win %": "49.16%",
    "Role %": "98.09%",
    "Pick %": "7.85%",
    "Ban %": "7.94%",
    "KDA": 2.31
  },
  {
    "Name": "Lillia",
    "Class": "Fighter",
    "Role": "JUNGLE",
    "Tier": "A",
    "Score": 52.03,
    "Trend": -3.96,
    "Win %": "50.35%",
    "Role %": "82.50%",
    "Pick %": "4.72%",
    "Ban %": "2.29%",
    "KDA": 2.7
  },
  {
    "Name": "Lillia",
    "Class": "Fighter",
    "Role": "TOP",
    "Tier": "B",
    "Score": 41.35,
    "Trend": 7.39,
    "Win %": "52.23%",
    "Role %": "13.92%",
    "Pick %": "0.84%",
    "Ban %": "2.21%",
    "KDA": 2
  },
  {
    "Name": "Lissandra",
    "Class": "Mage",
    "Role": "MID",
    "Tier": "A",
    "Score": 48.46,
    "Trend": 0.35,
    "Win %": "50.86%",
    "Role %": "90.83%",
    "Pick %": "2.58%",
    "Ban %": "0.81%",
    "KDA": 2.29
  },
  {
    "Name": "Lucian",
    "Class": "Marksman",
    "Role": "ADC",
    "Tier": "God",
    "Score": 87.01,
    "Trend": -0.08,
    "Win %": "51.84%",
    "Role %": "88.68%",
    "Pick %": "17.48%",
    "Ban %": "18.71%",
    "KDA": 2.3
  },
  {
    "Name": "Lulu",
    "Class": "Support",
    "Role": "SUPPORT",
    "Tier": "S",
    "Score": 71.61,
    "Trend": -3.38,
    "Win %": "50.54%",
    "Role %": "95.26%",
    "Pick %": "8.69%",
    "Ban %": "15.27%",
    "KDA": 3.01
  },
  {
    "Name": "Lux",
    "Class": "Mage",
    "Role": "SUPPORT",
    "Tier": "S",
    "Score": 68.94,
    "Trend": -6.85,
    "Win %": "48.84%",
    "Role %": "62.40%",
    "Pick %": "9.99%",
    "Ban %": "9.09%",
    "KDA": 2.41
  },
  {
    "Name": "Lux",
    "Class": "Mage",
    "Role": "MID",
    "Tier": "S",
    "Score": 60.28,
    "Trend": -0.78,
    "Win %": "50.84%",
    "Role %": "34.08%",
    "Pick %": "4.92%",
    "Ban %": "9.09%",
    "KDA": 2.74
  },
  {
    "Name": "Malphite",
    "Class": "Tank",
    "Role": "TOP",
    "Tier": "A",
    "Score": 57.47,
    "Trend": -1.28,
    "Win %": "50.93%",
    "Role %": "72.33%",
    "Pick %": "3.64%",
    "Ban %": "3.59%",
    "KDA": 2.23
  },
  {
    "Name": "Malphite",
    "Class": "Tank",
    "Role": "MID",
    "Tier": "B",
    "Score": 39.81,
    "Trend": -0.95,
    "Win %": "49.57%",
    "Role %": "12.45%",
    "Pick %": "0.63%",
    "Ban %": "3.59%",
    "KDA": 2.3
  },
  {
    "Name": "Malphite",
    "Class": "Tank",
    "Role": "SUPPORT",
    "Tier": "D",
    "Score": 28.53,
    "Trend": -3.31,
    "Win %": "45.74%",
    "Role %": "13.57%",
    "Pick %": "0.75%",
    "Ban %": "3.57%",
    "KDA": 1.95
  },
  {
    "Name": "Malzahar",
    "Class": "Mage",
    "Role": "MID",
    "Tier": "A",
    "Score": 50.16,
    "Trend": -0.68,
    "Win %": "51.68%",
    "Role %": "91.18%",
    "Pick %": "2.91%",
    "Ban %": "3.24%",
    "KDA": 2.08
  },
  {
    "Name": "Maokai",
    "Class": "Tank",
    "Role": "SUPPORT",
    "Tier": "B",
    "Score": 40.32,
    "Trend": 6.01,
    "Win %": "51.00%",
    "Role %": "76.16%",
    "Pick %": "1.05%",
    "Ban %": "0.11%",
    "KDA": 2.15
  },
  {
    "Name": "Maokai",
    "Class": "Tank",
    "Role": "TOP",
    "Tier": "C",
    "Score": 34.52,
    "Trend": 9.74,
    "Win %": "50.87%",
    "Role %": "16.98%",
    "Pick %": "0.28%",
    "Ban %": "0.11%",
    "KDA": 1.99
  },
  {
    "Name": "Master Yi",
    "Class": "Assassin",
    "Role": "JUNGLE",
    "Tier": "S",
    "Score": 62.22,
    "Trend": -15.14,
    "Win %": "49.62%",
    "Role %": "90.90%",
    "Pick %": "6.47%",
    "Ban %": "17.86%",
    "KDA": 1.97
  },
  {
    "Name": "Miss Fortune",
    "Class": "Marksman",
    "Role": "ADC",
    "Tier": "S",
    "Score": 58.89,
    "Trend": -15.38,
    "Win %": "50.35%",
    "Role %": "93.13%",
    "Pick %": "11.32%",
    "Ban %": "3.61%",
    "KDA": 2.19
  },
  {
    "Name": "Mordekaiser",
    "Class": "Fighter",
    "Role": "TOP",
    "Tier": "God",
    "Score": 83.44,
    "Trend": -5.33,
    "Win %": "50.35%",
    "Role %": "81.21%",
    "Pick %": "7.95%",
    "Ban %": "9.23%",
    "KDA": 1.8
  },
  {
    "Name": "Mordekaiser",
    "Class": "Fighter",
    "Role": "JUNGLE",
    "Tier": "C",
    "Score": 38.12,
    "Trend": 2.94,
    "Win %": "51.47%",
    "Role %": "13.23%",
    "Pick %": "1.34%",
    "Ban %": "9.94%",
    "KDA": 2.33
  },
  {
    "Name": "Morgana",
    "Class": "Mage",
    "Role": "SUPPORT",
    "Tier": "S",
    "Score": 61.52,
    "Trend": -6.27,
    "Win %": "48.56%",
    "Role %": "87.39%",
    "Pick %": "6.70%",
    "Ban %": "23.21%",
    "KDA": 2.38
  },
  {
    "Name": "Nami",
    "Class": "Support",
    "Role": "SUPPORT",
    "Tier": "God",
    "Score": 86.73,
    "Trend": -0.09,
    "Win %": "51.60%",
    "Role %": "99.55%",
    "Pick %": "13.36%",
    "Ban %": "6.93%",
    "KDA": 3.19
  },
  {
    "Name": "Nasus",
    "Class": "Fighter",
    "Role": "TOP",
    "Tier": "A",
    "Score": 50.78,
    "Trend": -5.37,
    "Win %": "49.38%",
    "Role %": "76.12%",
    "Pick %": "3.74%",
    "Ban %": "3.40%",
    "KDA": 1.75
  },
  {
    "Name": "Nasus",
    "Class": "Fighter",
    "Role": "MID",
    "Tier": "C",
    "Score": 35.6,
    "Trend": 0,
    "Win %": "48.23%",
    "Role %": "12.69%",
    "Pick %": "0.37%",
    "Ban %": "3.40%",
    "KDA": 2.13
  },
  {
    "Name": "Nautilus",
    "Class": "Tank",
    "Role": "SUPPORT",
    "Tier": "God",
    "Score": 77.72,
    "Trend": -2.88,
    "Win %": "50.69%",
    "Role %": "97.92%",
    "Pick %": "11.00%",
    "Ban %": "16.38%",
    "KDA": 2.35
  },
  {
    "Name": "Neeko",
    "Class": "Mage",
    "Role": "MID",
    "Tier": "A",
    "Score": 49.89,
    "Trend": -2.15,
    "Win %": "53.11%",
    "Role %": "55.59%",
    "Pick %": "1.80%",
    "Ban %": "0.59%",
    "KDA": 2.28
  },
  {
    "Name": "Neeko",
    "Class": "Mage",
    "Role": "SUPPORT",
    "Tier": "D",
    "Score": 33.66,
    "Trend": 0.85,
    "Win %": "48.31%",
    "Role %": "25.46%",
    "Pick %": "0.82%",
    "Ban %": "0.59%",
    "KDA": 1.96
  },
  {
    "Name": "Neeko",
    "Class": "Mage",
    "Role": "TOP",
    "Tier": "D",
    "Score": 25.64,
    "Trend": -1.41,
    "Win %": "47.88%",
    "Role %": "10.67%",
    "Pick %": "0.29%",
    "Ban %": "0.59%",
    "KDA": 1.76
  },
  {
    "Name": "Nidalee",
    "Class": "Assassin",
    "Role": "JUNGLE",
    "Tier": "A",
    "Score": 50.32,
    "Trend": -4.62,
    "Win %": "48.23%",
    "Role %": "90.15%",
    "Pick %": "5.10%",
    "Ban %": "4.59%",
    "KDA": 2.83
  },
  {
    "Name": "Nocturne",
    "Class": "Assassin",
    "Role": "JUNGLE",
    "Tier": "S",
    "Score": 61.47,
    "Trend": -5.43,
    "Win %": "52.80%",
    "Role %": "94.91%",
    "Pick %": "5.36%",
    "Ban %": "6.01%",
    "KDA": 2.64
  },
  {
    "Name": "Nunu",
    "Class": "Tank",
    "Role": "JUNGLE",
    "Tier": "B",
    "Score": 44.9,
    "Trend": 5.87,
    "Win %": "50.65%",
    "Role %": "87.11%",
    "Pick %": "2.82%",
    "Ban %": "1.23%",
    "KDA": 2.8
  },
  {
    "Name": "Olaf",
    "Class": "Fighter",
    "Role": "TOP",
    "Tier": "S",
    "Score": 62.9,
    "Trend": 54.24,
    "Win %": "53.18%",
    "Role %": "46.39%",
    "Pick %": "3.96%",
    "Ban %": "8.89%",
    "KDA": 1.79
  },
  {
    "Name": "Olaf",
    "Class": "Fighter",
    "Role": "JUNGLE",
    "Tier": "A",
    "Score": 54.61,
    "Trend": 39.7,
    "Win %": "51.94%",
    "Role %": "51.48%",
    "Pick %": "4.57%",
    "Ban %": "8.89%",
    "KDA": 2.37
  },
  {
    "Name": "Orianna",
    "Class": "Mage",
    "Role": "MID",
    "Tier": "B",
    "Score": 41.78,
    "Trend": -3.9,
    "Win %": "47.54%",
    "Role %": "91.85%",
    "Pick %": "2.22%",
    "Ban %": "0.17%",
    "KDA": 2.41
  },
  {
    "Name": "Ornn",
    "Class": "Tank",
    "Role": "TOP",
    "Tier": "S",
    "Score": 59.69,
    "Trend": -2.96,
    "Win %": "50.96%",
    "Role %": "92.72%",
    "Pick %": "4.07%",
    "Ban %": "0.71%",
    "KDA": 2.26
  },
  {
    "Name": "Pantheon",
    "Class": "Fighter",
    "Role": "MID",
    "Tier": "B",
    "Score": 46.09,
    "Trend": 1.12,
    "Win %": "51.67%",
    "Role %": "27.59%",
    "Pick %": "1.44%",
    "Ban %": "1.10%",
    "KDA": 2.27
  },
  {
    "Name": "Pantheon",
    "Class": "Fighter",
    "Role": "TOP",
    "Tier": "C",
    "Score": 39.4,
    "Trend": 1.71,
    "Win %": "50.76%",
    "Role %": "21.56%",
    "Pick %": "1.13%",
    "Ban %": "1.14%",
    "KDA": 1.99
  },
  {
    "Name": "Pantheon",
    "Class": "Fighter",
    "Role": "SUPPORT",
    "Tier": "C",
    "Score": 37.01,
    "Trend": 1.85,
    "Win %": "47.70%",
    "Role %": "43.90%",
    "Pick %": "2.33%",
    "Ban %": "1.10%",
    "KDA": 1.93
  },
  {
    "Name": "Poppy",
    "Class": "Tank",
    "Role": "TOP",
    "Tier": "B",
    "Score": 40.98,
    "Trend": 0.23,
    "Win %": "50.24%",
    "Role %": "36.92%",
    "Pick %": "1.56%",
    "Ban %": "2.11%",
    "KDA": 2
  },
  {
    "Name": "Poppy",
    "Class": "Tank",
    "Role": "JUNGLE",
    "Tier": "C",
    "Score": 36.22,
    "Trend": -2.84,
    "Win %": "48.71%",
    "Role %": "52.54%",
    "Pick %": "2.25%",
    "Ban %": "2.11%",
    "KDA": 2.55
  },
  {
    "Name": "Pyke",
    "Class": "Support",
    "Role": "SUPPORT",
    "Tier": "S",
    "Score": 71.35,
    "Trend": -16.91,
    "Win %": "48.18%",
    "Role %": "92.21%",
    "Pick %": "10.19%",
    "Ban %": "21.73%",
    "KDA": 2.11
  },
  {
    "Name": "Qiyana",
    "Class": "Assassin",
    "Role": "MID",
    "Tier": "A",
    "Score": 49.14,
    "Trend": -0.21,
    "Win %": "49.31%",
    "Role %": "67.76%",
    "Pick %": "3.88%",
    "Ban %": "6.22%",
    "KDA": 1.99
  },
  {
    "Name": "Qiyana",
    "Class": "Assassin",
    "Role": "JUNGLE",
    "Tier": "D",
    "Score": 31.35,
    "Trend": -0.03,
    "Win %": "48.23%",
    "Role %": "27.57%",
    "Pick %": "1.57%",
    "Ban %": "6.22%",
    "KDA": 2.37
  },
  {
    "Name": "Quinn",
    "Class": "Marksman",
    "Role": "TOP",
    "Tier": "B",
    "Score": 44.37,
    "Trend": 0.97,
    "Win %": "51.90%",
    "Role %": "79.44%",
    "Pick %": "1.70%",
    "Ban %": "1.10%",
    "KDA": 1.82
  },
  {
    "Name": "Rakan",
    "Class": "Support",
    "Role": "SUPPORT",
    "Tier": "A",
    "Score": 50.05,
    "Trend": -1.07,
    "Win %": "49.61%",
    "Role %": "98.33%",
    "Pick %": "4.19%",
    "Ban %": "0.29%",
    "KDA": 2.81
  },
  {
    "Name": "Rammus",
    "Class": "Tank",
    "Role": "JUNGLE",
    "Tier": "B",
    "Score": 44.59,
    "Trend": -2.37,
    "Win %": "51.22%",
    "Role %": "94.75%",
    "Pick %": "2.33%",
    "Ban %": "3.87%",
    "KDA": 2.83
  },
  {
    "Name": "Rek'Sai",
    "Class": "Fighter",
    "Role": "JUNGLE",
    "Tier": "B",
    "Score": 45.15,
    "Trend": 0.02,
    "Win %": "51.12%",
    "Role %": "96.42%",
    "Pick %": "2.94%",
    "Ban %": "3.84%",
    "KDA": 2.51
  },
  {
    "Name": "Rell",
    "Class": "Tank",
    "Role": "SUPPORT",
    "Tier": "B",
    "Score": 41.71,
    "Trend": 0.16,
    "Win %": "50.04%",
    "Role %": "97.89%",
    "Pick %": "1.78%",
    "Ban %": "0.30%",
    "KDA": 2.39
  },
  {
    "Name": "Renata Glasc",
    "Class": "Support",
    "Role": "SUPPORT",
    "Tier": "S",
    "Score": 65.3,
    "Trend": -5.69,
    "Win %": "52.64%",
    "Role %": "99.00%",
    "Pick %": "6.70%",
    "Ban %": "7.36%",
    "KDA": 2.83
  },
  {
    "Name": "Renekton",
    "Class": "Fighter",
    "Role": "TOP",
    "Tier": "A",
    "Score": 53.41,
    "Trend": 13.46,
    "Win %": "49.22%",
    "Role %": "84.14%",
    "Pick %": "4.18%",
    "Ban %": "2.45%",
    "KDA": 1.85
  },
  {
    "Name": "Renekton",
    "Class": "Fighter",
    "Role": "MID",
    "Tier": "B",
    "Score": 42.19,
    "Trend": 6.18,
    "Win %": "51.47%",
    "Role %": "14.06%",
    "Pick %": "0.64%",
    "Ban %": "2.45%",
    "KDA": 2.09
  },
  {
    "Name": "Rengar",
    "Class": "Assassin",
    "Role": "JUNGLE",
    "Tier": "S",
    "Score": 60,
    "Trend": -8.89,
    "Win %": "51.45%",
    "Role %": "74.21%",
    "Pick %": "5.28%",
    "Ban %": "19.30%",
    "KDA": 2.3
  },
  {
    "Name": "Rengar",
    "Class": "Assassin",
    "Role": "TOP",
    "Tier": "B",
    "Score": 41.36,
    "Trend": 2.34,
    "Win %": "49.84%",
    "Role %": "21.77%",
    "Pick %": "1.62%",
    "Ban %": "19.30%",
    "KDA": 1.82
  },
  {
    "Name": "Riven",
    "Class": "Fighter",
    "Role": "TOP",
    "Tier": "S",
    "Score": 68.41,
    "Trend": -4.61,
    "Win %": "50.96%",
    "Role %": "89.76%",
    "Pick %": "5.75%",
    "Ban %": "4.92%",
    "KDA": 1.86
  },
  {
    "Name": "Rumble",
    "Class": "Fighter",
    "Role": "MID",
    "Tier": "A",
    "Score": 47.62,
    "Trend": -0.62,
    "Win %": "52.90%",
    "Role %": "27.49%",
    "Pick %": "0.77%",
    "Ban %": "0.49%",
    "KDA": 2.55
  },
  {
    "Name": "Rumble",
    "Class": "Fighter",
    "Role": "TOP",
    "Tier": "C",
    "Score": 34.76,
    "Trend": 0.68,
    "Win %": "47.94%",
    "Role %": "56.31%",
    "Pick %": "1.44%",
    "Ban %": "0.49%",
    "KDA": 2.03
  },
  {
    "Name": "Rumble",
    "Class": "Fighter",
    "Role": "JUNGLE",
    "Tier": "D",
    "Score": 20.57,
    "Trend": 3.54,
    "Win %": "45.60%",
    "Role %": "10.43%",
    "Pick %": "0.25%",
    "Ban %": "0.41%",
    "KDA": 2.66
  },
  {
    "Name": "Ryze",
    "Class": "Mage",
    "Role": "MID",
    "Tier": "D",
    "Score": 26.98,
    "Trend": -2.99,
    "Win %": "42.48%",
    "Role %": "80.20%",
    "Pick %": "1.34%",
    "Ban %": "0.13%",
    "KDA": 1.89
  },
  {
    "Name": "Ryze",
    "Class": "Mage",
    "Role": "TOP",
    "Tier": "D",
    "Score": 14.47,
    "Trend": 4.29,
    "Win %": "43.82%",
    "Role %": "16.52%",
    "Pick %": "0.28%",
    "Ban %": "0.14%",
    "KDA": 1.59
  },
  {
    "Name": "Samira",
    "Class": "Marksman",
    "Role": "ADC",
    "Tier": "God",
    "Score": 73.6,
    "Trend": 0.15,
    "Win %": "51.89%",
    "Role %": "96.81%",
    "Pick %": "12.43%",
    "Ban %": "24.37%",
    "KDA": 2.25
  },
  {
    "Name": "Sejuani",
    "Class": "Tank",
    "Role": "JUNGLE",
    "Tier": "A",
    "Score": 47.77,
    "Trend": -1.47,
    "Win %": "52.12%",
    "Role %": "71.27%",
    "Pick %": "2.09%",
    "Ban %": "0.31%",
    "KDA": 3.21
  },
  {
    "Name": "Sejuani",
    "Class": "Tank",
    "Role": "TOP",
    "Tier": "D",
    "Score": 30.54,
    "Trend": -3.87,
    "Win %": "48.00%",
    "Role %": "21.07%",
    "Pick %": "0.55%",
    "Ban %": "0.31%",
    "KDA": 2.16
  },
  {
    "Name": "Senna",
    "Class": "Marksman",
    "Role": "SUPPORT",
    "Tier": "God",
    "Score": 89.39,
    "Trend": -4,
    "Win %": "53.05%",
    "Role %": "92.25%",
    "Pick %": "13.70%",
    "Ban %": "9.54%",
    "KDA": 2.67
  },
  {
    "Name": "Seraphine",
    "Class": "Mage",
    "Role": "SUPPORT",
    "Tier": "B",
    "Score": 43.99,
    "Trend": 2.08,
    "Win %": "49.03%",
    "Role %": "69.37%",
    "Pick %": "3.12%",
    "Ban %": "0.74%",
    "KDA": 2.41
  },
  {
    "Name": "Seraphine",
    "Class": "Mage",
    "Role": "ADC",
    "Tier": "B",
    "Score": 42.7,
    "Trend": 8.06,
    "Win %": "53.93%",
    "Role %": "14.86%",
    "Pick %": "0.58%",
    "Ban %": "0.77%",
    "KDA": 2.84
  },
  {
    "Name": "Seraphine",
    "Class": "Mage",
    "Role": "MID",
    "Tier": "B",
    "Score": 41.17,
    "Trend": -1.63,
    "Win %": "49.72%",
    "Role %": "13.70%",
    "Pick %": "0.57%",
    "Ban %": "0.77%",
    "KDA": 2.55
  },
  {
    "Name": "Sett",
    "Class": "Fighter",
    "Role": "TOP",
    "Tier": "S",
    "Score": 70.08,
    "Trend": -5.32,
    "Win %": "50.14%",
    "Role %": "76.86%",
    "Pick %": "6.44%",
    "Ban %": "5.81%",
    "KDA": 1.69
  },
  {
    "Name": "Sett",
    "Class": "Fighter",
    "Role": "SUPPORT",
    "Tier": "C",
    "Score": 35.69,
    "Trend": 6.78,
    "Win %": "49.17%",
    "Role %": "12.77%",
    "Pick %": "0.83%",
    "Ban %": "5.81%",
    "KDA": 2.02
  },
  {
    "Name": "Shaco",
    "Class": "Assassin",
    "Role": "JUNGLE",
    "Tier": "A",
    "Score": 57.87,
    "Trend": -7.56,
    "Win %": "49.98%",
    "Role %": "82.20%",
    "Pick %": "5.19%",
    "Ban %": "16.65%",
    "KDA": 2.72
  },
  {
    "Name": "Shaco",
    "Class": "Assassin",
    "Role": "SUPPORT",
    "Tier": "C",
    "Score": 36.48,
    "Trend": -0.49,
    "Win %": "48.26%",
    "Role %": "14.88%",
    "Pick %": "1.02%",
    "Ban %": "18.71%",
    "KDA": 2.33
  },
  {
    "Name": "Shen",
    "Class": "Tank",
    "Role": "TOP",
    "Tier": "S",
    "Score": 67.33,
    "Trend": 2.85,
    "Win %": "53.06%",
    "Role %": "83.92%",
    "Pick %": "3.74%",
    "Ban %": "0.82%",
    "KDA": 2.86
  },
  {
    "Name": "Shen",
    "Class": "Tank",
    "Role": "SUPPORT",
    "Tier": "C",
    "Score": 36.73,
    "Trend": 4.02,
    "Win %": "48.77%",
    "Role %": "11.93%",
    "Pick %": "0.47%",
    "Ban %": "0.81%",
    "KDA": 2.72
  },
  {
    "Name": "Shyvana",
    "Class": "Fighter",
    "Role": "JUNGLE",
    "Tier": "A",
    "Score": 50.26,
    "Trend": -0.38,
    "Win %": "52.43%",
    "Role %": "88.18%",
    "Pick %": "3.20%",
    "Ban %": "1.33%",
    "KDA": 2.71
  },
  {
    "Name": "Shyvana",
    "Class": "Fighter",
    "Role": "TOP",
    "Tier": "C",
    "Score": 34.92,
    "Trend": 0,
    "Win %": "50.79%",
    "Role %": "10.07%",
    "Pick %": "0.37%",
    "Ban %": "1.46%",
    "KDA": 1.99
  },
  {
    "Name": "Singed",
    "Class": "Tank",
    "Role": "MID",
    "Tier": "A",
    "Score": 48.04,
    "Trend": -2.65,
    "Win %": "53.68%",
    "Role %": "15.26%",
    "Pick %": "0.35%",
    "Ban %": "0.42%",
    "KDA": 2.63
  },
  {
    "Name": "Singed",
    "Class": "Tank",
    "Role": "TOP",
    "Tier": "B",
    "Score": 44.46,
    "Trend": 2.42,
    "Win %": "51.55%",
    "Role %": "72.94%",
    "Pick %": "1.77%",
    "Ban %": "0.48%",
    "KDA": 1.91
  },
  {
    "Name": "Sion",
    "Class": "Tank",
    "Role": "TOP",
    "Tier": "A",
    "Score": 52.96,
    "Trend": -16.92,
    "Win %": "49.61%",
    "Role %": "80.76%",
    "Pick %": "4.46%",
    "Ban %": "3.12%",
    "KDA": 1.41
  },
  {
    "Name": "Sivir",
    "Class": "Marksman",
    "Role": "ADC",
    "Tier": "B",
    "Score": 40.29,
    "Trend": -5.2,
    "Win %": "50.54%",
    "Role %": "95.01%",
    "Pick %": "3.54%",
    "Ban %": "0.81%",
    "KDA": 2.39
  },
  {
    "Name": "Skarner",
    "Class": "Fighter",
    "Role": "TOP",
    "Tier": "C",
    "Score": 38.5,
    "Trend": 6.27,
    "Win %": "51.92%",
    "Role %": "23.92%",
    "Pick %": "0.18%",
    "Ban %": "0.14%",
    "KDA": 2.26
  },
  {
    "Name": "Skarner",
    "Class": "Fighter",
    "Role": "JUNGLE",
    "Tier": "C",
    "Score": 36.74,
    "Trend": 1.11,
    "Win %": "51.44%",
    "Role %": "72.65%",
    "Pick %": "0.58%",
    "Ban %": "0.14%",
    "KDA": 2.76
  },
  {
    "Name": "Sona",
    "Class": "Support",
    "Role": "SUPPORT",
    "Tier": "A",
    "Score": 55.7,
    "Trend": 3.97,
    "Win %": "53.46%",
    "Role %": "97.26%",
    "Pick %": "3.54%",
    "Ban %": "0.44%",
    "KDA": 2.86
  },
  {
    "Name": "Soraka",
    "Class": "Support",
    "Role": "SUPPORT",
    "Tier": "S",
    "Score": 63.52,
    "Trend": -1.3,
    "Win %": "52.08%",
    "Role %": "93.97%",
    "Pick %": "6.77%",
    "Ban %": "5.81%",
    "KDA": 2.72
  },
  {
    "Name": "Swain",
    "Class": "Mage",
    "Role": "ADC",
    "Tier": "A",
    "Score": 51.43,
    "Trend": 6.69,
    "Win %": "56.79%",
    "Role %": "17.12%",
    "Pick %": "1.49%",
    "Ban %": "6.46%",
    "KDA": 2.93
  },
  {
    "Name": "Swain",
    "Class": "Mage",
    "Role": "MID",
    "Tier": "A",
    "Score": 51.21,
    "Trend": -5.18,
    "Win %": "52.21%",
    "Role %": "22.86%",
    "Pick %": "2.28%",
    "Ban %": "6.46%",
    "KDA": 2.45
  },
  {
    "Name": "Swain",
    "Class": "Mage",
    "Role": "SUPPORT",
    "Tier": "A",
    "Score": 51.12,
    "Trend": -0.09,
    "Win %": "50.76%",
    "Role %": "39.71%",
    "Pick %": "4.16%",
    "Ban %": "6.46%",
    "KDA": 2.36
  },
  {
    "Name": "Swain",
    "Class": "Mage",
    "Role": "TOP",
    "Tier": "B",
    "Score": 46.84,
    "Trend": -3.96,
    "Win %": "51.19%",
    "Role %": "20.23%",
    "Pick %": "1.89%",
    "Ban %": "6.46%",
    "KDA": 2.14
  },
  {
    "Name": "Sylas",
    "Class": "Mage",
    "Role": "MID",
    "Tier": "S",
    "Score": 63.44,
    "Trend": 1.21,
    "Win %": "50.00%",
    "Role %": "82.52%",
    "Pick %": "7.63%",
    "Ban %": "4.43%",
    "KDA": 2.12
  },
  {
    "Name": "Sylas",
    "Class": "Mage",
    "Role": "TOP",
    "Tier": "D",
    "Score": 33.4,
    "Trend": 0.49,
    "Win %": "48.93%",
    "Role %": "11.71%",
    "Pick %": "1.05%",
    "Ban %": "4.42%",
    "KDA": 1.82
  },
  {
    "Name": "Syndra",
    "Class": "Mage",
    "Role": "MID",
    "Tier": "B",
    "Score": 42.78,
    "Trend": 0.88,
    "Win %": "48.08%",
    "Role %": "85.43%",
    "Pick %": "2.68%",
    "Ban %": "0.89%",
    "KDA": 2.11
  },
  {
    "Name": "Tahm Kench",
    "Class": "Support",
    "Role": "ADC",
    "Tier": "A",
    "Score": 51.4,
    "Trend": 2.15,
    "Win %": "57.71%",
    "Role %": "20.88%",
    "Pick %": "0.67%",
    "Ban %": "1.97%",
    "KDA": 2.98
  },
  {
    "Name": "Tahm Kench",
    "Class": "Support",
    "Role": "TOP",
    "Tier": "B",
    "Score": 47.27,
    "Trend": 7.1,
    "Win %": "50.60%",
    "Role %": "48.83%",
    "Pick %": "1.93%",
    "Ban %": "1.97%",
    "KDA": 2.42
  },
  {
    "Name": "Tahm Kench",
    "Class": "Support",
    "Role": "SUPPORT",
    "Tier": "D",
    "Score": 32.79,
    "Trend": 1.29,
    "Win %": "46.63%",
    "Role %": "27.97%",
    "Pick %": "1.03%",
    "Ban %": "1.97%",
    "KDA": 2.35
  },
  {
    "Name": "Taliyah",
    "Class": "Mage",
    "Role": "MID",
    "Tier": "S",
    "Score": 71.94,
    "Trend": 33.01,
    "Win %": "53.42%",
    "Role %": "48.41%",
    "Pick %": "7.17%",
    "Ban %": "12.54%",
    "KDA": 2.21
  },
  {
    "Name": "Taliyah",
    "Class": "Mage",
    "Role": "JUNGLE",
    "Tier": "A",
    "Score": 54.83,
    "Trend": 36.02,
    "Win %": "49.48%",
    "Role %": "37.58%",
    "Pick %": "5.34%",
    "Ban %": "12.54%",
    "KDA": 2.42
  },
  {
    "Name": "Talon",
    "Class": "Assassin",
    "Role": "JUNGLE",
    "Tier": "A",
    "Score": 50.76,
    "Trend": -1.37,
    "Win %": "50.12%",
    "Role %": "54.72%",
    "Pick %": "4.68%",
    "Ban %": "5.79%",
    "KDA": 2.46
  },
  {
    "Name": "Talon",
    "Class": "Assassin",
    "Role": "MID",
    "Tier": "A",
    "Score": 50.28,
    "Trend": 4.43,
    "Win %": "50.35%",
    "Role %": "43.00%",
    "Pick %": "3.52%",
    "Ban %": "5.79%",
    "KDA": 2.11
  },
  {
    "Name": "Taric",
    "Class": "Support",
    "Role": "SUPPORT",
    "Tier": "B",
    "Score": 43.87,
    "Trend": 4.33,
    "Win %": "51.45%",
    "Role %": "87.48%",
    "Pick %": "1.03%",
    "Ban %": "0.13%",
    "KDA": 2.8
  },
  {
    "Name": "Teemo",
    "Class": "Marksman",
    "Role": "TOP",
    "Tier": "S",
    "Score": 62.4,
    "Trend": -0.93,
    "Win %": "51.08%",
    "Role %": "76.86%",
    "Pick %": "4.66%",
    "Ban %": "7.88%",
    "KDA": 1.71
  },
  {
    "Name": "Thresh",
    "Class": "Support",
    "Role": "SUPPORT",
    "Tier": "S",
    "Score": 60.31,
    "Trend": 7.92,
    "Win %": "48.64%",
    "Role %": "97.90%",
    "Pick %": "8.27%",
    "Ban %": "2.34%",
    "KDA": 2.61
  },
  {
    "Name": "Tristana",
    "Class": "Marksman",
    "Role": "ADC",
    "Tier": "A",
    "Score": 53.67,
    "Trend": -2.45,
    "Win %": "51.81%",
    "Role %": "85.69%",
    "Pick %": "7.97%",
    "Ban %": "3.96%",
    "KDA": 2.27
  },
  {
    "Name": "Tristana",
    "Class": "Marksman",
    "Role": "MID",
    "Tier": "B",
    "Score": 41.31,
    "Trend": -2.87,
    "Win %": "50.63%",
    "Role %": "11.91%",
    "Pick %": "0.89%",
    "Ban %": "3.96%",
    "KDA": 2.05
  },
  {
    "Name": "Trundle",
    "Class": "Fighter",
    "Role": "JUNGLE",
    "Tier": "B",
    "Score": 43.19,
    "Trend": -2.67,
    "Win %": "51.41%",
    "Role %": "64.82%",
    "Pick %": "2.29%",
    "Ban %": "1.99%",
    "KDA": 2.59
  },
  {
    "Name": "Trundle",
    "Class": "Fighter",
    "Role": "TOP",
    "Tier": "C",
    "Score": 36.71,
    "Trend": 2.76,
    "Win %": "51.05%",
    "Role %": "29.85%",
    "Pick %": "1.04%",
    "Ban %": "2.13%",
    "KDA": 1.61
  },
  {
    "Name": "Tryndamere",
    "Class": "Fighter",
    "Role": "TOP",
    "Tier": "A",
    "Score": 49.97,
    "Trend": -2.46,
    "Win %": "49.25%",
    "Role %": "83.29%",
    "Pick %": "3.45%",
    "Ban %": "10.10%",
    "KDA": 1.74
  },
  {
    "Name": "Twisted Fate",
    "Class": "Mage",
    "Role": "MID",
    "Tier": "B",
    "Score": 41.12,
    "Trend": 1.45,
    "Win %": "47.00%",
    "Role %": "90.59%",
    "Pick %": "2.86%",
    "Ban %": "0.20%",
    "KDA": 2.08
  },
  {
    "Name": "Twitch",
    "Class": "Marksman",
    "Role": "ADC",
    "Tier": "A",
    "Score": 51.34,
    "Trend": 1.17,
    "Win %": "52.62%",
    "Role %": "78.04%",
    "Pick %": "6.10%",
    "Ban %": "4.79%",
    "KDA": 2.39
  },
  {
    "Name": "Udyr",
    "Class": "Fighter",
    "Role": "JUNGLE",
    "Tier": "C",
    "Score": 37.42,
    "Trend": 2.66,
    "Win %": "50.50%",
    "Role %": "91.62%",
    "Pick %": "1.58%",
    "Ban %": "0.51%",
    "KDA": 2.54
  },
  {
    "Name": "Urgot",
    "Class": "Fighter",
    "Role": "TOP",
    "Tier": "A",
    "Score": 52.93,
    "Trend": 2.32,
    "Win %": "51.79%",
    "Role %": "92.47%",
    "Pick %": "3.07%",
    "Ban %": "1.77%",
    "KDA": 1.88
  },
  {
    "Name": "Varus",
    "Class": "Marksman",
    "Role": "ADC",
    "Tier": "D",
    "Score": 29.5,
    "Trend": -1.11,
    "Win %": "46.14%",
    "Role %": "89.53%",
    "Pick %": "3.27%",
    "Ban %": "0.28%",
    "KDA": 2.2
  },
  {
    "Name": "Vayne",
    "Class": "Marksman",
    "Role": "ADC",
    "Tier": "A",
    "Score": 54.81,
    "Trend": -7.77,
    "Win %": "50.19%",
    "Role %": "81.23%",
    "Pick %": "9.10%",
    "Ban %": "14.31%",
    "KDA": 2.07
  },
  {
    "Name": "Vayne",
    "Class": "Marksman",
    "Role": "TOP",
    "Tier": "C",
    "Score": 39.07,
    "Trend": -0.63,
    "Win %": "49.80%",
    "Role %": "16.44%",
    "Pick %": "1.76%",
    "Ban %": "14.31%",
    "KDA": 1.53
  },
  {
    "Name": "Veigar",
    "Class": "Mage",
    "Role": "MID",
    "Tier": "S",
    "Score": 62.18,
    "Trend": -4.18,
    "Win %": "51.13%",
    "Role %": "72.32%",
    "Pick %": "6.25%",
    "Ban %": "7.64%",
    "KDA": 2.23
  },
  {
    "Name": "Veigar",
    "Class": "Mage",
    "Role": "ADC",
    "Tier": "B",
    "Score": 41,
    "Trend": 0.22,
    "Win %": "53.24%",
    "Role %": "17.34%",
    "Pick %": "1.57%",
    "Ban %": "7.64%",
    "KDA": 2.38
  },
  {
    "Name": "Vel'Koz",
    "Class": "Mage",
    "Role": "SUPPORT",
    "Tier": "B",
    "Score": 42.11,
    "Trend": 0.75,
    "Win %": "50.88%",
    "Role %": "58.21%",
    "Pick %": "1.72%",
    "Ban %": "0.45%",
    "KDA": 2.15
  },
  {
    "Name": "Vel'Koz",
    "Class": "Mage",
    "Role": "MID",
    "Tier": "B",
    "Score": 41.26,
    "Trend": -4.81,
    "Win %": "49.11%",
    "Role %": "36.89%",
    "Pick %": "1.14%",
    "Ban %": "0.48%",
    "KDA": 2.43
  },
  {
    "Name": "Vex",
    "Class": "Mage",
    "Role": "MID",
    "Tier": "S",
    "Score": 59.22,
    "Trend": -0.26,
    "Win %": "50.57%",
    "Role %": "91.82%",
    "Pick %": "5.46%",
    "Ban %": "9.25%",
    "KDA": 2.33
  },
  {
    "Name": "Vi",
    "Class": "Fighter",
    "Role": "JUNGLE",
    "Tier": "B",
    "Score": 46.53,
    "Trend": -5.23,
    "Win %": "50.22%",
    "Role %": "92.70%",
    "Pick %": "4.18%",
    "Ban %": "1.75%",
    "KDA": 2.27
  },
  {
    "Name": "Viego",
    "Class": "Assassin",
    "Role": "JUNGLE",
    "Tier": "God",
    "Score": 91.79,
    "Trend": 2.09,
    "Win %": "49.37%",
    "Role %": "93.44%",
    "Pick %": "13.57%",
    "Ban %": "10.17%",
    "KDA": 2.36
  },
  {
    "Name": "Viktor",
    "Class": "Mage",
    "Role": "MID",
    "Tier": "A",
    "Score": 54.31,
    "Trend": -2.13,
    "Win %": "49.93%",
    "Role %": "91.21%",
    "Pick %": "5.00%",
    "Ban %": "2.67%",
    "KDA": 2.16
  },
  {
    "Name": "Vladimir",
    "Class": "Mage",
    "Role": "MID",
    "Tier": "A",
    "Score": 55.05,
    "Trend": -1.38,
    "Win %": "50.15%",
    "Role %": "68.81%",
    "Pick %": "4.65%",
    "Ban %": "7.55%",
    "KDA": 2.28
  },
  {
    "Name": "Vladimir",
    "Class": "Mage",
    "Role": "TOP",
    "Tier": "C",
    "Score": 38.02,
    "Trend": -0.3,
    "Win %": "48.49%",
    "Role %": "29.38%",
    "Pick %": "1.75%",
    "Ban %": "7.55%",
    "KDA": 1.93
  },
  {
    "Name": "Volibear",
    "Class": "Fighter",
    "Role": "JUNGLE",
    "Tier": "S",
    "Score": 62.68,
    "Trend": -5.7,
    "Win %": "52.46%",
    "Role %": "59.17%",
    "Pick %": "5.65%",
    "Ban %": "6.09%",
    "KDA": 2.76
  },
  {
    "Name": "Volibear",
    "Class": "Fighter",
    "Role": "TOP",
    "Tier": "A",
    "Score": 50.81,
    "Trend": -2.8,
    "Win %": "49.39%",
    "Role %": "38.54%",
    "Pick %": "3.76%",
    "Ban %": "6.09%",
    "KDA": 1.66
  },
  {
    "Name": "Warwick",
    "Class": "Fighter",
    "Role": "JUNGLE",
    "Tier": "A",
    "Score": 51.57,
    "Trend": -2.07,
    "Win %": "51.65%",
    "Role %": "74.20%",
    "Pick %": "4.45%",
    "Ban %": "4.42%",
    "KDA": 2.17
  },
  {
    "Name": "Warwick",
    "Class": "Fighter",
    "Role": "TOP",
    "Tier": "C",
    "Score": 38.58,
    "Trend": 3.87,
    "Win %": "51.21%",
    "Role %": "23.65%",
    "Pick %": "1.01%",
    "Ban %": "4.42%",
    "KDA": 1.8
  },
  {
    "Name": "Wukong",
    "Class": "Fighter",
    "Role": "JUNGLE",
    "Tier": "S",
    "Score": 67.41,
    "Trend": -0.98,
    "Win %": "53.07%",
    "Role %": "61.01%",
    "Pick %": "6.15%",
    "Ban %": "7.75%",
    "KDA": 2.8
  },
  {
    "Name": "Wukong",
    "Class": "Fighter",
    "Role": "TOP",
    "Tier": "A",
    "Score": 56.43,
    "Trend": 0.23,
    "Win %": "51.12%",
    "Role %": "33.00%",
    "Pick %": "3.44%",
    "Ban %": "7.75%",
    "KDA": 2.06
  },
  {
    "Name": "Xayah",
    "Class": "Marksman",
    "Role": "ADC",
    "Tier": "C",
    "Score": 38.66,
    "Trend": -6.38,
    "Win %": "48.39%",
    "Role %": "97.65%",
    "Pick %": "5.06%",
    "Ban %": "1.95%",
    "KDA": 2.2
  },
  {
    "Name": "Xerath",
    "Class": "Mage",
    "Role": "MID",
    "Tier": "A",
    "Score": 55.61,
    "Trend": 2.66,
    "Win %": "51.94%",
    "Role %": "40.96%",
    "Pick %": "2.96%",
    "Ban %": "4.22%",
    "KDA": 2.98
  },
  {
    "Name": "Xerath",
    "Class": "Mage",
    "Role": "SUPPORT",
    "Tier": "A",
    "Score": 54,
    "Trend": 1.69,
    "Win %": "52.25%",
    "Role %": "53.88%",
    "Pick %": "3.99%",
    "Ban %": "4.22%",
    "KDA": 2.57
  },
  {
    "Name": "Xin Zhao",
    "Class": "Fighter",
    "Role": "JUNGLE",
    "Tier": "C",
    "Score": 37.21,
    "Trend": 3.7,
    "Win %": "49.63%",
    "Role %": "87.39%",
    "Pick %": "2.45%",
    "Ban %": "1.04%",
    "KDA": 2.23
  },
  {
    "Name": "Yasuo",
    "Class": "Fighter",
    "Role": "MID",
    "Tier": "God",
    "Score": 87.8,
    "Trend": -1.66,
    "Win %": "50.11%",
    "Role %": "67.72%",
    "Pick %": "11.72%",
    "Ban %": "25.07%",
    "KDA": 1.73
  },
  {
    "Name": "Yasuo",
    "Class": "Fighter",
    "Role": "TOP",
    "Tier": "B",
    "Score": 44.99,
    "Trend": -4.12,
    "Win %": "49.18%",
    "Role %": "14.88%",
    "Pick %": "2.46%",
    "Ban %": "25.07%",
    "KDA": 1.47
  },
  {
    "Name": "Yasuo",
    "Class": "Fighter",
    "Role": "ADC",
    "Tier": "B",
    "Score": 43,
    "Trend": 0.67,
    "Win %": "53.12%",
    "Role %": "16.33%",
    "Pick %": "2.67%",
    "Ban %": "25.07%",
    "KDA": 2
  },
  {
    "Name": "Yone",
    "Class": "Assassin",
    "Role": "MID",
    "Tier": "S",
    "Score": 66.11,
    "Trend": -0.55,
    "Win %": "49.78%",
    "Role %": "60.89%",
    "Pick %": "7.94%",
    "Ban %": "15.13%",
    "KDA": 1.81
  },
  {
    "Name": "Yone",
    "Class": "Assassin",
    "Role": "TOP",
    "Tier": "S",
    "Score": 58.22,
    "Trend": -2.22,
    "Win %": "49.99%",
    "Role %": "35.52%",
    "Pick %": "4.34%",
    "Ban %": "15.13%",
    "KDA": 1.58
  },
  {
    "Name": "Yorick",
    "Class": "Fighter",
    "Role": "TOP",
    "Tier": "B",
    "Score": 47.06,
    "Trend": -6.62,
    "Win %": "51.60%",
    "Role %": "94.03%",
    "Pick %": "2.60%",
    "Ban %": "3.51%",
    "KDA": 1.49
  },
  {
    "Name": "Yuumi",
    "Class": "Support",
    "Role": "SUPPORT",
    "Tier": "God",
    "Score": 94.97,
    "Trend": 1.86,
    "Win %": "49.81%",
    "Role %": "98.90%",
    "Pick %": "12.27%",
    "Ban %": "26.51%",
    "KDA": 4.05
  },
  {
    "Name": "Zac",
    "Class": "Tank",
    "Role": "JUNGLE",
    "Tier": "A",
    "Score": 54.47,
    "Trend": -4.02,
    "Win %": "51.77%",
    "Role %": "81.51%",
    "Pick %": "3.44%",
    "Ban %": "2.79%",
    "KDA": 3.42
  },
  {
    "Name": "Zed",
    "Class": "Assassin",
    "Role": "MID",
    "Tier": "God",
    "Score": 80.84,
    "Trend": -0.19,
    "Win %": "49.86%",
    "Role %": "71.48%",
    "Pick %": "8.42%",
    "Ban %": "35.79%",
    "KDA": 2.19
  },
  {
    "Name": "Zed",
    "Class": "Assassin",
    "Role": "JUNGLE",
    "Tier": "B",
    "Score": 42.29,
    "Trend": -3.44,
    "Win %": "48.08%",
    "Role %": "24.57%",
    "Pick %": "2.71%",
    "Ban %": "35.79%",
    "KDA": 2.45
  },
  {
    "Name": "Zeri",
    "Class": "Marksman",
    "Role": "ADC",
    "Tier": "D",
    "Score": 29.14,
    "Trend": 0.01,
    "Win %": "45.68%",
    "Role %": "92.08%",
    "Pick %": "3.70%",
    "Ban %": "3.66%",
    "KDA": 2.07
  },
  {
    "Name": "Ziggs",
    "Class": "Mage",
    "Role": "MID",
    "Tier": "B",
    "Score": 40.5,
    "Trend": -2.28,
    "Win %": "49.58%",
    "Role %": "29.65%",
    "Pick %": "0.85%",
    "Ban %": "0.44%",
    "KDA": 2.3
  },
  {
    "Name": "Ziggs",
    "Class": "Mage",
    "Role": "ADC",
    "Tier": "C",
    "Score": 34.08,
    "Trend": -4.45,
    "Win %": "49.99%",
    "Role %": "62.05%",
    "Pick %": "1.66%",
    "Ban %": "0.43%",
    "KDA": 2.33
  },
  {
    "Name": "Zilean",
    "Class": "Support",
    "Role": "MID",
    "Tier": "A",
    "Score": 53.09,
    "Trend": 4.02,
    "Win %": "54.04%",
    "Role %": "18.27%",
    "Pick %": "0.61%",
    "Ban %": "1.59%",
    "KDA": 3.29
  },
  {
    "Name": "Zilean",
    "Class": "Support",
    "Role": "SUPPORT",
    "Tier": "A",
    "Score": 49.49,
    "Trend": 3.8,
    "Win %": "50.96%",
    "Role %": "77.56%",
    "Pick %": "2.69%",
    "Ban %": "1.81%",
    "KDA": 3.11
  },
  {
    "Name": "Zoe",
    "Class": "Mage",
    "Role": "MID",
    "Tier": "A",
    "Score": 55.13,
    "Trend": 5.52,
    "Win %": "48.44%",
    "Role %": "90.55%",
    "Pick %": "5.81%",
    "Ban %": "2.01%",
    "KDA": 2.34
  },
  {
    "Name": "Zyra",
    "Class": "Mage",
    "Role": "SUPPORT",
    "Tier": "B",
    "Score": 46.65,
    "Trend": -2.51,
    "Win %": "50.83%",
    "Role %": "90.23%",
    "Pick %": "3.20%",
    "Ban %": "1.83%",
    "KDA": 2.13
  }
]